anatool/__init__.py
anatool/plotting.py
anatool/statistics.py
anatool/submit.py
anatool/data/5S_onresonance.dat
anatool/data/continuum.dat
anatool/data/on_resonance.dat
belle_analysis_tool-1.3.0.dist-info/LICENSE
belle_analysis_tool-1.3.0.dist-info/METADATA
belle_analysis_tool-1.3.0.dist-info/WHEEL
belle_analysis_tool-1.3.0.dist-info/top_level.txt
belle_analysis_tool-1.3.0.dist-info/RECORD
