Metadata-Version: 2.1
Name: belle-analysis-tool
Version: 1.3.0
Summary: A package that helps you do analysis for Belle or Belle II
Home-page: https://github.com/Yuan-Ru-Lin/belle-analysis-tool
Author: Yuan-Ru Lin
Author-email: yuanrulin.tw@gmail.com
License: UNKNOWN
Project-URL: Bug Tracker, https://github.com/Yuan-Ru-Lin/belle-analysis-tool/issues
Platform: UNKNOWN
Classifier: Programming Language :: Python :: 3
Classifier: License :: OSI Approved :: MIT License
Classifier: Operating System :: OS Independent
Classifier: Topic :: Scientific/Engineering :: Physics
Classifier: Intended Audience :: Science/Research
Requires-Python: >=3.6
License-File: LICENSE
